norman_ai/__init__.py
norman_ai/norman_functions.py
norman_ai/data/norman_model1.h5
norman_ai-0.1.0.dist-info/LICENSE.txt
norman_ai-0.1.0.dist-info/METADATA
norman_ai-0.1.0.dist-info/WHEEL
norman_ai-0.1.0.dist-info/top_level.txt
norman_ai-0.1.0.dist-info/RECORD
