Metadata-Version: 2.1
Name: norman_ai
Version: 0.1.0
Summary: A package for automation of the novel object recognition test.
Home-page: https://github.com/Seyij/norman
Author: seyij_p
Author-email: seyi.ooj@gmail.com
Classifier: Programming Language :: Python :: 3
Classifier: License :: OSI Approved :: GNU General Public License v3 (GPLv3)
Classifier: Operating System :: Microsoft :: Windows :: Windows 10
Requires-Python: >=3.6
License-File: LICENSE.txt
